krepe.py
krepe-0.2.0.dist-info/LICENSE
krepe-0.2.0.dist-info/METADATA
krepe-0.2.0.dist-info/WHEEL
krepe-0.2.0.dist-info/entry_points.txt
krepe-0.2.0.dist-info/top_level.txt
krepe-0.2.0.dist-info/RECORD
