Metadata-Version: 2.1
Name: krepe
Version: 0.2.0
Summary: A package to count k-mers and calculate/plot De Bruijn graphs, occurence bar graphs, venn diagrams, and dendrograms.
Home-page: https://github.com/RGBwalnut/Kmer-Counting-Analysis
Author: Aengus McGuinness, and Erika Pedersen
Author-email: erikalaraine2@gmail.com
License: GPLv3
Platform: UNKNOWN
Classifier: Programming Language :: Python :: 3.8
Classifier: License :: OSI Approved :: GNU General Public License v3 (GPLv3)
Classifier: Operating System :: OS Independent
Requires-Python: >=3
Requires-Dist: matplotlib
Requires-Dist: matplotlib-venn
Requires-Dist: numpy
Requires-Dist: psutil
Requires-Dist: sourmash
Requires-Dist: toyplot
